pygeist/__init__.py
pygeist/__main__.py
pygeist/_adapter.so
pygeist/adapter.py
pygeist/api.py
pygeist/exceptions.py
pygeist/idleness_handler.py
pygeist/main.py
pygeist/registry.py
pygeist/request.py
pygeist/router.py
pygeist/server.py
pygeist/sessions.py
pygeist/testclient.py
pygeist/unrequested_message.py
pygeist/zeitgeist.py
pygeist/abstract/__init__.py
pygeist/abstract/api.py
pygeist/abstract/endpoint.py
pygeist/abstract/idleness_handler.py
pygeist/abstract/methods_handler.py
pygeist/concurrency/__init__.py
pygeist/concurrency/helpers.py
pygeist/concurrency/multiprocess.py
pygeist/predefined_routes/__init__.py
pygeist/predefined_routes/info_retriever.py
pygeist/predefined_routes/ping.py
pygeist/utils/__init__.py
pygeist/utils/signature.py
pygeist/utils/singleton.py
pygeist/utils/status_code.py
pygeist-0.4.0.dist-info/licenses/LICENSE
pygeist-0.4.0.dist-info/METADATA
pygeist-0.4.0.dist-info/WHEEL
pygeist-0.4.0.dist-info/top_level.txt
pygeist-0.4.0.dist-info/RECORD
