Metadata-Version: 2.4
Name: pygeist
Version: 0.4.0
Summary: Pygeist server package
Requires-Python: >=3.10
License-File: LICENSE
Requires-Dist: pydantic
Dynamic: description
Dynamic: description-content-type
Dynamic: license-file
Dynamic: requires-dist
Dynamic: requires-python
Dynamic: summary
